topology_processor/Untitled.ipynb
topology_processor/__init__.py
topology_processor/__main__.py
topology_processor/blazegraph.py
topology_processor/dist_api_message.json
topology_processor/distributedtopology.py
topology_processor/gridappsd-topology-daemon.config
topology_processor/gridappsd-topology-service.config
topology_processor/networkmodel.py
topology_processor/topo_meas_queries.py
topology_processor/topo_tester.py
topology_processor/topologydictionary.py
gridappsd_topology_processor-2023.6.1.dist-info/LICENSE
gridappsd_topology_processor-2023.6.1.dist-info/METADATA
gridappsd_topology_processor-2023.6.1.dist-info/WHEEL
gridappsd_topology_processor-2023.6.1.dist-info/RECORD
