Metadata-Version: 2.1
Name: gridappsd-topology-processor
Version: 2023.6.1
Summary: 
Home-page: https://github.com/GRIDAPPSD/topology-processor
License: BSD-3-Clause
Author: A. Anderson
Author-email: 19935503+AAndersn@users.noreply.github.com
Maintainer: A. Anderson
Maintainer-email: 19935503+AAndersn@users.noreply.github.com
Requires-Python: >=3.8,<4.0
Classifier: License :: OSI Approved :: BSD License
Classifier: Programming Language :: Python :: 3
Classifier: Programming Language :: Python :: 3.8
Classifier: Programming Language :: Python :: 3.9
Classifier: Programming Language :: Python :: 3.10
Classifier: Programming Language :: Python :: 3.11
Requires-Dist: gridappsd-python (>=2023.5.1a9,<2024.0.0)
Project-URL: Documentation, https://github.com/GRIDAPPSD/topology-processor
Project-URL: Repository, https://github.com/GRIDAPPSD/topology-processor
